pastasauce
