Metadata-Version: 1.0
Name: pastasauce
Version: 0.1.6
Summary: Sauce Labs interface for Python 3 exposing more of the SLAPI
Home-page: http://openstax.org
Author: OpenStax QA
Author-email: greg@openstax.org
License: Creative Commons Attribution 4.0 International Public License
Platform: UNKNOWN
